aergia/__init__.py
aergia/__main__.py
aergia/_cli/__init__.py
aergia/_cli/_command/__init__.py
aergia/_cli/_command/_chat.py
aergia/_cli/_command/_code.py
aergia/_cli/_command/_execute.py
aergia/_cli/_command/_image.py
aergia/_cli/_command/_info.py
aergia/_cli/_command/_models.py
aergia/_cli/_command/_parser.py
aergia/_cli/_command/_repl.py
aergia/_cli/_command/_role.py
aergia/_cli/_command/_session.py
aergia/_cli/_command/_tui.py
aergia/_cli/_command/_utilities.py
aergia/_cli/_io.py
aergia/_client.py
aergia/_config/__init__.py
aergia/_config/_cli.py
aergia/_config/_env.py
aergia/_config/_settings.py
aergia/_config/_toml.py
aergia/_db/__init__.py
aergia/_db/init.sql
aergia/_logging.py
aergia/_model/__init__.py
aergia/_model/_data.py
aergia/_model/_load.py
aergia/_model/_save.py
aergia/_model/_storage.py
aergia/_roles/__init__.py
aergia/_roles/_schemas.py
aergia/_roles/babelfish.role
aergia/_roles/babelfish.role.meta
aergia/_roles/convert.role
aergia/_roles/convert.role.meta
aergia/_roles/doc-py.role
aergia/_roles/doc-py.role.meta
aergia/_roles/doc-rs.role
aergia/_roles/doc-rs.role.meta
aergia/_roles/doc.role
aergia/_roles/doc.role.meta
aergia/_roles/editor.role
aergia/_roles/editor.role.meta
aergia/_roles/idiomatic.role
aergia/_roles/idiomatic.role.meta
aergia/_roles/pair.role
aergia/_roles/pair.role.meta
aergia/_roles/synonyms.role
aergia/_roles/synonyms.role.meta
aergia/_roles/typos.role
aergia/_roles/typos.role.meta
aergia/application.py
aergia-0.4.0.dist-info/METADATA
aergia-0.4.0.dist-info/WHEEL
aergia-0.4.0.dist-info/entry_points.txt
aergia-0.4.0.dist-info/RECORD
